ODENet/__init__.py
ODENet/dataScaling.py
ODENet/layers.py
ODENet/models.py
ODENet/utils.py
ODENet-0.0.5.dist-info/LICENSE
ODENet-0.0.5.dist-info/METADATA
ODENet-0.0.5.dist-info/WHEEL
ODENet-0.0.5.dist-info/top_level.txt
ODENet-0.0.5.dist-info/RECORD
