Metadata-Version: 2.1
Name: ODENet
Version: 0.0.5
Summary: A small example package
Home-page: https://github.com/uqyge/ODENet
Author: Y.Ge
Author-email: y.ge1222@gmail.com
License: UNKNOWN
Platform: UNKNOWN
Classifier: Programming Language :: Python :: 3
Classifier: License :: OSI Approved :: MIT License
Classifier: Operating System :: OS Independent
